LICENSE
MANIFEST.in
README.md
pyproject.toml
setup.py
pcangsd/__init__.py
pcangsd/admixture.py
pcangsd/admixture_cy.c
pcangsd/admixture_cy.pyx
pcangsd/covariance.py
pcangsd/covariance_cy.c
pcangsd/covariance_cy.pyx
pcangsd/inbreed.py
pcangsd/inbreed_cy.c
pcangsd/inbreed_cy.pyx
pcangsd/main.py
pcangsd/reader_cy.cpp
pcangsd/reader_cy.pyx
pcangsd/selection.py
pcangsd/shared.py
pcangsd/shared_cy.c
pcangsd/shared_cy.pyx
pcangsd/tree.py
pcangsd/tree_cy.c
pcangsd/tree_cy.pyx
pcangsd.egg-info/PKG-INFO
pcangsd.egg-info/SOURCES.txt
pcangsd.egg-info/dependency_links.txt
pcangsd.egg-info/entry_points.txt
pcangsd.egg-info/requires.txt
pcangsd.egg-info/top_level.txt