Metadata-Version: 2.2
Name: pcangsd
Version: 1.36.0
Summary: Framework for analyzing low depth NGS data in heterogeneous populations using PCA
Home-page: https://github.com/Rosemeis/pcangsd
Author: Jonas Meisner
Author-email: meisnerucph@gmail.com
Classifier: Programming Language :: Python :: 3
Classifier: License :: OSI Approved :: GNU General Public License v3 (GPLv3)
Classifier: Operating System :: OS Independent
Classifier: Development Status :: 4 - Beta
Requires-Python: >=3.10
License-File: LICENSE
Requires-Dist: cython>3.0.0
Requires-Dist: numpy>2.0.0
Requires-Dist: scipy>1.14.0
Dynamic: author
Dynamic: author-email
Dynamic: classifier
Dynamic: description
Dynamic: description-content-type
Dynamic: home-page
Dynamic: requires-dist
Dynamic: requires-python
Dynamic: summary
